LICENSE
README.md
setup.cfg
setup.py
denzelxrt/__init__.py
denzelxrt.egg-info/PKG-INFO
denzelxrt.egg-info/SOURCES.txt
denzelxrt.egg-info/dependency_links.txt
denzelxrt.egg-info/top_level.txt
denzelxrt/logs/__init__.py
denzelxrt/logs/abstract_logger.py
denzelxrt/logs/default_logger.py