Metadata-Version: 2.1
Name: denzelxrt
Version: 0.0.1
Summary: Logger for my tools (thanks body)
Author: denzelxrt
Author-email: pypi@denzel.lol
Classifier: Programming Language :: Python :: 3
Classifier: License :: OSI Approved :: MIT License
Classifier: Operating System :: OS Independent
Requires-Python: >=3.6
License-File: LICENSE
